[
    {
        "option_name": "scope",
        "type": "str",
        "choices": [
            "NODE",
            "CLUSTER",
            "PARTITION"
        ],
        "description": [
            "Use this option to gather data on the present node, all cluster nodes, or for the specified partitions. The CLUSTER scope generates smaller abbreviated archives for all nodes. The PARTITION scope collects the admin partition in addition to those specified. The partitionName option is only required for the PARTITION scope.",
            "Default value: NODE",
            "Possible values = NODE, CLUSTER, PARTITION"
        ],
        "is_get_id": false,
        "is_delete_id": false,
        "is_updateable": false
    },
    {
        "option_name": "partitionname",
        "type": "str",
        "description": [
            "Name of the partition.",
            "Minimum length =  1"
        ],
        "is_get_id": false,
        "is_delete_id": false,
        "is_updateable": false
    },
    {
        "option_name": "upload",
        "type": "bool",
        "description": [
            "Securely upload the collector archive to Citrix Technical Support using SSL. MyCitrix credentials will be required. If used with the -file option, no new collector archive is generated. Instead, the specified archive is uploaded. Note that the upload operation time depends on the size of the archive file, and the connection bandwidth."
        ],
        "is_get_id": false,
        "is_delete_id": false,
        "is_updateable": false
    },
    {
        "option_name": "proxy",
        "type": "str",
        "description": [
            "Specifies the proxy server to be used when uploading a collector archive. Use this parameter if the Citrix ADC does not have direct internet connectivity. The basic format of the proxy string is: \"proxy_IP:<proxy_port>\" (without quotes). If the proxy requires authentication the format is: \"username:password@proxy_IP:<proxy_port>\"."
        ],
        "is_get_id": false,
        "is_delete_id": false,
        "is_updateable": false
    },
    {
        "option_name": "casenumber",
        "type": "str",
        "description": [
            "Specifies the associated case or service request number if it has already been opened with Citrix Technical Support."
        ],
        "is_get_id": false,
        "is_delete_id": false,
        "is_updateable": false
    },
    {
        "option_name": "file",
        "type": "str",
        "description": [
            "Specifies the name (with full path) of the collector archive file to be uploaded. If this is specified, no new collector archive is generated."
        ],
        "is_get_id": false,
        "is_delete_id": false,
        "is_updateable": false
    },
    {
        "option_name": "description",
        "type": "str",
        "description": [
            "Provides a text description for the the upload, and can be used for logging purposes."
        ],
        "is_get_id": false,
        "is_delete_id": false,
        "is_updateable": false
    },
    {
        "option_name": "username",
        "type": "str",
        "description": [
            "Specifies My Citrix user name, which is used to login to Citrix upload server."
        ],
        "is_get_id": false,
        "is_delete_id": false,
        "is_updateable": false
    },
    {
        "option_name": "password",
        "type": "str",
        "description": [
            "Specifies My Citrix password, which is used to login to Citrix upload server."
        ],
        "is_get_id": false,
        "is_delete_id": false,
        "is_updateable": false
    }
]