[
    {
        "option_name": "translationinternalip",
        "type": "str",
        "description": [
            "IP address of the server for which you want to associate an external IP address. (Clients access the server through the associated external address and port.).",
            "Default value: 0"
        ],
        "is_get_id": false,
        "is_delete_id": true,
        "is_updateable": false
    },
    {
        "option_name": "accesstype",
        "type": "str",
        "choices": [
            "UserDevice",
            "Gateway",
            "UserDeviceAndGateway"
        ],
        "description": [
            "Type of access to the XenApp or XenDesktop server.                              Available settings function as follows:                             * User Device - Clients can use the translated address of the mapping entry to connect to the XenApp or XenDesktop server.                             * Gateway - Access Gateway can use the translated address of the mapping entry to connect to the XenApp or XenDesktop server.                             * User Device and Gateway - Both clients and Access Gateway can use the translated address of the mapping entry to connect to the XenApp or XenDesktop server.",
            "Default value: UserDevice",
            "Possible values = UserDevice, Gateway, UserDeviceAndGateway"
        ],
        "is_get_id": false,
        "is_delete_id": false,
        "is_updateable": false
    },
    {
        "option_name": "translationinternalport",
        "type": "int",
        "description": [
            "Port number of the server for which you want to associate an external port.  (Clients access the server through the associated external address and port.).",
            "Range 1 - 65535",
            "* in CLI is represented as 65535 in NITRO API"
        ],
        "is_get_id": false,
        "is_delete_id": true,
        "is_updateable": false
    },
    {
        "option_name": "translationexternalip",
        "type": "str",
        "description": [
            "External IP address associated with server's IP address."
        ],
        "is_get_id": false,
        "is_delete_id": true,
        "is_updateable": false
    },
    {
        "option_name": "translationexternalport",
        "type": "int",
        "description": [
            "External port number associated with the server's port number.",
            "Range 1 - 65535",
            "* in CLI is represented as 65535 in NITRO API"
        ],
        "is_get_id": false,
        "is_delete_id": true,
        "is_updateable": false
    },
    {
        "option_name": "sitepath",
        "type": "str",
        "description": [
            "Path to the Web Interface site.",
            "Minimum length =  1",
            "Maximum length =  250"
        ],
        "is_get_id": true,
        "is_delete_id": true,
        "is_updateable": false
    }
]